_clstm.so
clstm.py
clstm-0.0.5.dist-info/DESCRIPTION.rst
clstm-0.0.5.dist-info/METADATA
clstm-0.0.5.dist-info/metadata.json
clstm-0.0.5.dist-info/RECORD
clstm-0.0.5.dist-info/top_level.txt
clstm-0.0.5.dist-info/WHEEL
